kowanasutil/ApiHandler.py
kowanasutil/ApiResult.py
kowanasutil/Config.py
kowanasutil/DBConnection.py
kowanasutil/DBField.py
kowanasutil/DBFieldUID.py
kowanasutil/DBModel.py
kowanasutil/KowanasTime.py
kowanasutil/Log.py
kowanasutil/Scheduler.py
kowanasutil/Service.py
kowanasutil/Singleton.py
kowanasutil/Task.py
kowanasutil/__init__.py
tests/SingletonClass.py
tests/__init__.py
tests/test_Config.py
tests/test_SingletonClass.py
kowanasutil-0.0.5.dist-info/METADATA
kowanasutil-0.0.5.dist-info/WHEEL
kowanasutil-0.0.5.dist-info/top_level.txt
kowanasutil-0.0.5.dist-info/RECORD
