Metadata-Version: 2.1
Name: kowanasutil
Version: 0.0.5
Summary: kowanas utility
Home-page: https://github.com/Kowanas/kowanasuti
Author: kowanas
Author-email: saramsoftware@gmail.com
License: UNKNOWN
Project-URL: Bug Tracker, https://github.com/Kowanas/kowanasuti/issues
Platform: UNKNOWN
Classifier: Programming Language :: Python :: 3
Classifier: License :: OSI Approved :: MIT License
Classifier: Operating System :: OS Independent
Requires-Python: >=3.6
